Cajero.v
module Cajero(
    input CLK,
    input RESET,
    input TARJETA_RECIBIDA,
    input [15:0] PIN,
    input [3:0] DIGITO,
    input DIGITO_STB,
    input TIPO_TRANS, //0 para deposito, 1 para retiro
    input [31:0] MONTO, // creo que va en el tb
    input MONTO_STB, //falta
    output reg BALANCE_ACTUALIZADO,
    output reg ENTREGAR_DINERO,
    output reg FONDOS_INSUFICIENTES, 
    output reg PIN_INCORRECTO,
    output reg [1:0] ADVERTENCIA,
    output reg BLOQUEO
);

reg [63:0] BALANCE= 64'b0000000000000000000000000000000000000000000000100100100111110000; //Registro interno para la plata que hay en la cuenta. Para el ejemplo, se usan 150mil colones, que seria 000000000000000100100100100111010000
//en binario y en 64 bits
reg [2:0] INTENTOS; //Registro interno que hay para validar los intentos 
reg [15:0] DIGITO_INTERNO;
reg [15:0] PROX_DIGITO; //Registro interno para almacenar el proximo digito para el siguiente flop
//Mi pin es 6767, en binario eso es 0110 0111 0110 0111
//La tarea debe funcionar para un solo pin? O para varios usuarios?
//Es para ver si se debe reiniciar el monto o no.

// Máquina de estados
always @(posedge CLK or negedge RESET) begin
    if (!RESET) begin
        DIGITO_INTERNO <= 16'b0000000000000000;
    end else begin 
        DIGITO_INTERNO <= PROX_DIGITO;
    end
end

always @(*) begin
    PROX_DIGITO=DIGITO_INTERNO;
    if (!RESET || TARJETA_RECIBIDA == 0 ) begin
        // Si no hay tarjeta en el cajero, se ponen las señales en 0
        INTENTOS <= 0;
        BLOQUEO <= 0;
        ADVERTENCIA <= 0;
        PIN_INCORRECTO <= 0;
        FONDOS_INSUFICIENTES <= 0;
        ENTREGAR_DINERO <= 0;
        BALANCE_ACTUALIZADO <= 0;

        // Aquí puedes agregar otras señales que necesiten reinicio
    end 
    else if (TARJETA_RECIBIDA && INTENTOS <=2 ) begin
        //PIN <= 16'b0110011101100111; //SE FIJA EL PIN EN EL VALOR QUE ES, ESTE ES EL PIN DE ENTRADA!!!!!!!!!!!!!
        case(DIGITO_INTERNO)
        16'b0000000000000000: begin
        if (DIGITO == 4'b0110 && DIGITO_STB == 1) begin //Si digito es 0110 (6), y digito_stb es 1, se fija el siguiente estado
            PROX_DIGITO = 16'b0000000000000110;
            PIN_INCORRECTO = 0;
            end
        else if (DIGITO_STB == 1) begin 
            PROX_DIGITO = 16'b0000000000000000;
            INTENTOS = INTENTOS+ 1;
            PIN_INCORRECTO = 1;
            end
        end
        16'b0000000000000110: begin 
        if (DIGITO == 4'b0111 && DIGITO_STB == 1) begin //Si digito es 0111 (7), y digito_stb es 1, se fija el siguiente estado
            PROX_DIGITO = 16'b0000000001100111;
            PIN_INCORRECTO = 0;
            end 
        else if (DIGITO_STB == 1) begin 
            PROX_DIGITO = 16'b0000000000000000;
            INTENTOS = INTENTOS+1;
            PIN_INCORRECTO = 1;
            end
        end 
        16'b0000000001100111: begin 
            if (DIGITO == 4'b0110 && DIGITO_STB == 1) begin
            PROX_DIGITO = 16'b0000011001110110;
            PIN_INCORRECTO = 0;
            end  
        else if (DIGITO_STB == 1) begin 
            PROX_DIGITO = 16'b0000000000000000;
            INTENTOS = INTENTOS+1;
            PIN_INCORRECTO = 1;
            end
        end

        16'b0000011001110110: begin
            if (DIGITO == 4'b0111 && DIGITO_STB == 1) begin
            PROX_DIGITO = 16'b0110011101100111;
            PIN_INCORRECTO = 0;
            end
            else if (DIGITO_STB == 1) begin 
            PROX_DIGITO = 16'b0000000000000000;
            INTENTOS = INTENTOS+1;
            PIN_INCORRECTO = 1;
            end
        end
        default: begin// Manejo de estado inesperado
        PROX_DIGITO = 16'b0000000000000000; 
        end
        endcase
        DIGITO_INTERNO = PROX_DIGITO;
            // Verificar si el PIN ingresado es correcto
            if (DIGITO_INTERNO == PIN) begin
                PIN_INCORRECTO = 0;
                if (TIPO_TRANS == 0) begin // Logica si se escoge DEPOSITAR
                    BALANCE = MONTO + BALANCE;
                    BALANCE_ACTUALIZADO <= 1;
                end else begin
                    if (MONTO > BALANCE) begin 
                        FONDOS_INSUFICIENTES <= 1;
                    end else begin 
                        BALANCE = BALANCE - MONTO;
                        BALANCE_ACTUALIZADO <= 1;
                        ENTREGAR_DINERO <= 1;
                    end
                end
            end 


    if (INTENTOS > 0 && INTENTOS ==2) begin
        ADVERTENCIA = 1;
    end
    else begin
        ADVERTENCIA = 0;
    end

    if (INTENTOS==3) begin
        BLOQUEO <= 1;
        ADVERTENCIA <= 0;
        PIN_INCORRECTO <= 1;
        FONDOS_INSUFICIENTES <= 0;
        ENTREGAR_DINERO <= 0;
        BALANCE_ACTUALIZADO <= 0;
    end 
    else begin 
        BLOQUEO=0;
    end
end
end

endmodule

tester.v
`timescale 1ns / 1ps 
module tester(
    output reg CLK,
    output reg RESET,
    output reg TARJETA_RECIBIDA,
    output reg [15:0] PIN,
    output reg [3:0] DIGITO,
    output reg DIGITO_STB,
    output reg TIPO_TRANS, //0 para deposito, 1 para retiro
    output reg [31:0] MONTO, // creo que va en el tb
    output reg MONTO_STB, //falta
    input BALANCE_ACTUALIZADO,
    input ENTREGAR_DINERO,
    input FONDOS_INSUFICIENTES, 
    input PIN_INCORRECTO,
    input [1:0] ADVERTENCIA,
    input BLOQUEO);



    initial begin
    CLK = 0;
    // Se alterna entre 0 y 1 cada 5 unidades de tiempo
     forever #5 CLK = ~CLK; // Ciclo de reloj de 10 unidades de tiempo
  end
  initial begin
  /////////////////////////////////////////////////////////////////////
  //Prueba 1, funcionamiento ideal, deposito
  RESET = 0; 
  TARJETA_RECIBIDA = 0; 
  PIN = 0;
  DIGITO = 0;
  DIGITO_STB = 0;
  TIPO_TRANS = 0;
  MONTO_STB = 0;
  MONTO = 0;
  #10;
  RESET = 1; 

  RESET = 1;
  TARJETA_RECIBIDA = 1;
  PIN = 16'b0110011101100111;

  MONTO = 32'b00000000000000100100100111110000;//150 mil
  MONTO_STB = 1;
  #10;
  MONTO_STB = 0;
  #10;

  DIGITO = 4'b0110; //Primer digito, este corresponde a 6
  DIGITO_STB = 1;
  #10;
  DIGITO_STB = 0;
  #10;

  DIGITO = 4'b0111; //Segundo digito, este corresponde a 7
  DIGITO_STB = 1;
  #10;
  DIGITO_STB = 0;
  #10;

  DIGITO = 4'b0110; //Primer digito, este corresponde a 6
  DIGITO_STB = 1;
  #10;
  DIGITO_STB = 0;
  #10;
  DIGITO = 4'b0111; //Segundo digito, este corresponde a 7
  DIGITO_STB = 1;
  #10;
  DIGITO_STB = 0;
  #10;
/////////////////////////////////////////////////////////////////
//Prueba 2, funcionamiento ideal, retiro con fondos insuficientes
  RESET = 0; 
  TARJETA_RECIBIDA = 0; 
  PIN = 0;
  DIGITO = 0;
  DIGITO_STB = 0;
  TIPO_TRANS = 0;
  MONTO_STB = 0;
  MONTO = 0;
  #10;
  RESET = 1; 

  RESET = 1;
  TARJETA_RECIBIDA = 1;
  TIPO_TRANS = 1;
  PIN = 16'b0110011101100111;
  MONTO = 32'b00000000000001010101011100110000; //350 mil para retirar
  MONTO_STB = 1;
  #10;
  MONTO_STB = 0;
  #10;

  TARJETA_RECIBIDA = 1;
  DIGITO = 4'b0110; //Primer digito, este corresponde a 6
  DIGITO_STB = 1;
  #10;
  DIGITO_STB = 0;
  #10;

  DIGITO = 4'b0111; //Segundo digito, este corresponde a 7
  DIGITO_STB = 1;
  #10;
  DIGITO_STB = 0;
  #10;

  DIGITO = 4'b0110; //Tercer digito, este corresponde a 6
  DIGITO_STB = 1;
  #10;
  DIGITO_STB = 0;
  #10;
  DIGITO = 4'b0111; //Cuarto digito, este corresponde a 7
  DIGITO_STB = 1;
  #10;
  DIGITO_STB = 0;
  #10;
/////////////////////////////////////////////////////////////////////
/////////////////////////////////////////////////////////////////
//Prueba 3, funcionamiento ideal, retiro con fondos suficientes
  RESET = 0; 
  TARJETA_RECIBIDA = 0; 
  PIN = 0;
  DIGITO = 0;
  DIGITO_STB = 0;
  TIPO_TRANS = 0;
  MONTO_STB = 0;
  MONTO = 0;
  #10;
  RESET = 1; 

  RESET = 1;
  TARJETA_RECIBIDA = 1;
  TIPO_TRANS = 1;
  PIN = 16'b0110011101100111;
  MONTO = 32'b00000000000001001001001111100000; //300 mil para retirar
  MONTO_STB = 1;
  #10;
  MONTO_STB = 0;
  #10;

  TARJETA_RECIBIDA = 1;
  DIGITO = 4'b0110; //Primer digito, este corresponde a 6
  DIGITO_STB = 1;
  #10;
  DIGITO_STB = 0;
  #10;

  DIGITO = 4'b0111; //Segundo digito, este corresponde a 7
  DIGITO_STB = 1;
  #10;
  DIGITO_STB = 0;
  #10;

  DIGITO = 4'b0110; //Tercer digito, este corresponde a 6
  DIGITO_STB = 1;
  #10;
  DIGITO_STB = 0;
  #10;
  DIGITO = 4'b0111; //Cuarto digito, este corresponde a 7
  DIGITO_STB = 1;
  #10;
  DIGITO_STB = 0;
  #10;
/////////////////////////////////////////////////////////////////////
//Prueba 4, funcionamiento no ideal, se levantan alertas y pines incorrectos, bloqueos, deposito.
  RESET = 0; 
  TARJETA_RECIBIDA = 0; 
  PIN = 0;
  DIGITO = 0;
  DIGITO_STB = 0;
  TIPO_TRANS = 0;
  MONTO_STB = 0;
  MONTO = 0;
  #10;
  RESET = 1; 

  RESET = 1;
  TARJETA_RECIBIDA = 1;
  PIN = 16'b0110011101100111;
  MONTO = 32'b00000000000000100100100111110000; //150 mil para depositar
  MONTO_STB = 1;
  #10;
  MONTO_STB = 0;
  #10;

  TARJETA_RECIBIDA = 1;
  DIGITO = 4'b0110; //Primer digito, este corresponde a 6
  DIGITO_STB = 1;
  #10;
  DIGITO_STB = 0;
  #10;

  DIGITO = 4'b0111; //Segundo digito, este corresponde a 7
  DIGITO_STB = 1;
  #10;
  DIGITO_STB = 0;
  #10;

  DIGITO = 4'b0001; //Tercer digito, este corresponde a 1. Como es incorrecto, se reinician los digitos.
  DIGITO_STB = 1;   //Contador de errores llega a 1.
  #10;              //Se levanta Pin Incorrecto.
  DIGITO_STB = 0;
  #10;
  DIGITO = 0;

  DIGITO = 4'b0110; //Primer digito, este corresponde a 6
  DIGITO_STB = 1;
  #10;
  DIGITO_STB = 0;
  #10;

  DIGITO = 4'b0111; //Segundo digito, este corresponde a 7
  DIGITO_STB = 1;
  #10;
  DIGITO_STB = 0;
  #10;

  DIGITO = 4'b0110; //Tercer digito, este corresponde a 6
  DIGITO_STB = 1;
  #10;
  DIGITO_STB = 0;
  #10;

  DIGITO = 4'b0001; //Cuarto digito, este corresponde a 1. Es incorrecto, se reinician los digitos.
  DIGITO_STB = 1;   // Contador de errores llega a 2. Se levanta una advertencia.
  #10;              // Se levanta Pin Incorrecto
  DIGITO_STB = 0;
  #10;

  DIGITO = 4'b0110; //Primer digito, este corresponde a 6.
  DIGITO_STB = 1;
  #10;
  DIGITO_STB = 0;
  #10;

  DIGITO = 4'b1001; //Segundo digito, este corresponde a 9.Es incorrecto, se reinician los digitos.
  DIGITO_STB = 1; //Contador de errores llega a 3. Se levanta un Bloqueo.
  #10;            //// Se levanta Pin Incorrecto
  DIGITO_STB = 0;
  #10;

  DIGITO = 4'b0110; //Primer digito, este corresponde a 6.
  DIGITO_STB = 1;
  #10;
  DIGITO_STB = 0;
  #10;

  DIGITO = 4'b0111; //Segundo digito, este corresponde a 7
  DIGITO_STB = 1;   //Como Bloqueo esta activo, hay que reiniciar todo para proceder.
  #10;
  DIGITO_STB = 0;
  #10;

  RESET = 0; //Reset
  DIGITO = 4'b0000;
  MONTO = 32'b00000000000000000000000000000000;
  DIGITO_STB = 1;
  #10;
  DIGITO_STB = 0;
  #10;
  

  RESET = 1;
  TARJETA_RECIBIDA = 1;
  PIN = 16'b0110011101100111;
  MONTO = 32'b00000000000000100100100111110000;//150 mil
  MONTO_STB = 1;
  #10;
  MONTO_STB = 0;
  #10;

  DIGITO = 4'b0110; //Primer digito, este corresponde a 6
  DIGITO_STB = 1;
  #10;
  DIGITO_STB = 0;
  #10;

  DIGITO = 4'b0111; //Segundo digito, este corresponde a 7
  DIGITO_STB = 1;
  #10;
  DIGITO_STB = 0;
  #10;

  DIGITO = 4'b0110; //Primer digito, este corresponde a 6
  DIGITO_STB = 1;
  #10;
  DIGITO_STB = 0;
  #10;
  DIGITO = 4'b0111; //Segundo digito, este corresponde a 7
  DIGITO_STB = 1;
  #10;
  DIGITO_STB = 0;
  #10;
/////////////////////////////////////////////////////////////////////
//Prueba 5, funcionamiento no ideal, se levantan alertas y pines incorrectos, bloqueos, retiro.
RESET = 0; 
  TARJETA_RECIBIDA = 0; 
  PIN = 0;
  DIGITO = 0;
  DIGITO_STB = 0;
  TIPO_TRANS = 1;
  MONTO_STB = 0;
  MONTO = 0;
  #10;
  RESET = 1; 

  RESET = 1;
  TARJETA_RECIBIDA = 1;
  PIN = 16'b0110011101100111;
  MONTO = 32'b00000000000000010010010011111000; //75 mil para retirar
  MONTO_STB = 1;
  #10;
  MONTO_STB = 0;
  #10;

  TARJETA_RECIBIDA = 1;
  DIGITO = 4'b0110; //Primer digito, este corresponde a 6
  DIGITO_STB = 1;
  #10;
  DIGITO_STB = 0;
  #10;

  DIGITO = 4'b0111; //Segundo digito, este corresponde a 7
  DIGITO_STB = 1;
  #10;
  DIGITO_STB = 0;
  #10;

  DIGITO = 4'b0001; //Tercer digito, este corresponde a 1. Como es incorrecto, se reinician los digitos.
  DIGITO_STB = 1;   //Contador de errores llega a 1.
  #10;              //Se levanta Pin Incorrecto.
  DIGITO_STB = 0;
  #10;
  DIGITO = 0;

  DIGITO = 4'b0110; //Primer digito, este corresponde a 6
  DIGITO_STB = 1;
  #10;
  DIGITO_STB = 0;
  #10;

  DIGITO = 4'b0111; //Segundo digito, este corresponde a 7
  DIGITO_STB = 1;
  #10;
  DIGITO_STB = 0;
  #10;

  DIGITO = 4'b0110; //Tercer digito, este corresponde a 6
  DIGITO_STB = 1;
  #10;
  DIGITO_STB = 0;
  #10;

  DIGITO = 4'b0001; //Cuarto digito, este corresponde a 1. Es incorrecto, se reinician los digitos.
  DIGITO_STB = 1;   // Contador de errores llega a 2. Se levanta una advertencia.
  #10;              // Se levanta Pin Incorrecto
  DIGITO_STB = 0;
  #10;

  DIGITO = 4'b0110; //Primer digito, este corresponde a 6.
  DIGITO_STB = 1;
  #10;
  DIGITO_STB = 0;
  #10;

  DIGITO = 4'b1001; //Segundo digito, este corresponde a 9.Es incorrecto, se reinician los digitos.
  DIGITO_STB = 1; //Contador de errores llega a 3. Se levanta un Bloqueo.
  #10;            //// Se levanta Pin Incorrecto
  DIGITO_STB = 0;
  #10;

  DIGITO = 4'b0110; //Primer digito, este corresponde a 6.
  DIGITO_STB = 1;
  #10;
  DIGITO_STB = 0;
  #10;

  DIGITO = 4'b0111; //Segundo digito, este corresponde a 7
  DIGITO_STB = 1;   //Como Bloqueo esta activo, hay que reiniciar todo para proceder.
  #10;
  DIGITO_STB = 0;
  #10;

  RESET = 0; //Reset
  DIGITO = 4'b0000;
  MONTO = 32'b00000000000000000000000000000000;
  DIGITO_STB = 1;
  #10;
  DIGITO_STB = 0;
  #10;
  

  RESET = 1;
  TARJETA_RECIBIDA = 1;
  PIN = 16'b0110011101100111;
  MONTO = 32'b00000000000000010010010011111000;//150 mil
  MONTO_STB = 1;
  #10;
  MONTO_STB = 0;
  #10;

  DIGITO = 4'b0110; //Primer digito, este corresponde a 6
  DIGITO_STB = 1;
  #10;
  DIGITO_STB = 0;
  #10;

  DIGITO = 4'b0111; //Segundo digito, este corresponde a 7
  DIGITO_STB = 1;
  #10;
  DIGITO_STB = 0;
  #10;

  DIGITO = 4'b0110; //Primer digito, este corresponde a 6
  DIGITO_STB = 1;
  #10;
  DIGITO_STB = 0;
  #10;
  DIGITO = 4'b0111; //Segundo digito, este corresponde a 7
  DIGITO_STB = 1;
  #10;
  DIGITO_STB = 0;
  #10;
  $finish;
  end
endmodule

Cajero_tb.v
`include "tester.v"
`include "Cajero.v"
                                        
// Testbench
module Cajero_tb;
  // Declaración de señales
  wire CLK, RESET;
  wire TARJETA_RECIBIDA, TIPO_TRANS, DIGITO_STB, MONTO_STB;
  wire [3:0] DIGITO;
  wire [15:0] PIN;
  wire [31:0] MONTO;
  wire BALANCE_ACTUALIZADO, ENTREGAR_DINERO, FONDOS_INSUFICIENTES, PIN_INCORRECTO, BLOQUEO;
  wire [1:0] ADVERTENCIA;

  // Instancia de tester
  tester P0 (
    .CLK (CLK), 
    .RESET (RESET), 
    .TARJETA_RECIBIDA (TARJETA_RECIBIDA),
    .TIPO_TRANS (TIPO_TRANS),
    .DIGITO_STB (DIGITO_STB),
    .MONTO_STB (MONTO_STB),
    .DIGITO (DIGITO),
    .PIN (PIN),
    .MONTO (MONTO),
    .BALANCE_ACTUALIZADO (BALANCE_ACTUALIZADO),
    .ENTREGAR_DINERO (ENTREGAR_DINERO),
    .FONDOS_INSUFICIENTES (FONDOS_INSUFICIENTES),
    .PIN_INCORRECTO (PIN_INCORRECTO),
    .BLOQUEO (BLOQUEO)
  );

  // Instancia de la unidad bajo prueba (UUT)
  Cajero uut (
    .CLK (CLK), 
    .RESET (RESET), 
    .TARJETA_RECIBIDA (TARJETA_RECIBIDA),
    .TIPO_TRANS (TIPO_TRANS),
    .DIGITO_STB (DIGITO_STB),
    .MONTO_STB (MONTO_STB),
    .DIGITO (DIGITO),
    .PIN (PIN),
    .MONTO (MONTO),
    .BALANCE_ACTUALIZADO (BALANCE_ACTUALIZADO),
    .ENTREGAR_DINERO (ENTREGAR_DINERO),
    .FONDOS_INSUFICIENTES (FONDOS_INSUFICIENTES),
    .PIN_INCORRECTO (PIN_INCORRECTO),
    .BLOQUEO (BLOQUEO)
  );


  // Dumpfile y monitor
  initial begin
    $dumpfile("resultados.vcd");
    $dumpvars(0, Cajero_tb);
  end

endmodule

resultados.vcd
$date
	Sat May 18 08:20:49 2024
$end
$version
	Icarus Verilog
$end
$timescale
	1ps
$end
$scope module Cajero_tb $end
$var wire 1 ! TIPO_TRANS $end
$var wire 1 " TARJETA_RECIBIDA $end
$var wire 1 # RESET $end
$var wire 1 $ PIN_INCORRECTO $end
$var wire 16 % PIN [15:0] $end
$var wire 1 & MONTO_STB $end
$var wire 32 ' MONTO [31:0] $end
$var wire 1 ( FONDOS_INSUFICIENTES $end
$var wire 1 ) ENTREGAR_DINERO $end
$var wire 1 * DIGITO_STB $end
$var wire 4 + DIGITO [3:0] $end
$var wire 1 , CLK $end
$var wire 1 - BLOQUEO $end
$var wire 1 . BALANCE_ACTUALIZADO $end
$scope module P0 $end
$var wire 2 / ADVERTENCIA [1:0] $end
$var wire 1 $ PIN_INCORRECTO $end
$var wire 1 ( FONDOS_INSUFICIENTES $end
$var wire 1 ) ENTREGAR_DINERO $end
$var wire 1 - BLOQUEO $end
$var wire 1 . BALANCE_ACTUALIZADO $end
$var reg 1 , CLK $end
$var reg 4 0 DIGITO [3:0] $end
$var reg 1 * DIGITO_STB $end
$var reg 32 1 MONTO [31:0] $end
$var reg 1 & MONTO_STB $end
$var reg 16 2 PIN [15:0] $end
$var reg 1 # RESET $end
$var reg 1 " TARJETA_RECIBIDA $end
$var reg 1 ! TIPO_TRANS $end
$upscope $end
$scope module uut $end
$var wire 1 , CLK $end
$var wire 4 3 DIGITO [3:0] $end
$var wire 1 * DIGITO_STB $end
$var wire 32 4 MONTO [31:0] $end
$var wire 1 & MONTO_STB $end
$var wire 16 5 PIN [15:0] $end
$var wire 1 # RESET $end
$var wire 1 " TARJETA_RECIBIDA $end
$var wire 1 ! TIPO_TRANS $end
$var reg 2 6 ADVERTENCIA [1:0] $end
$var reg 64 7 BALANCE [63:0] $end
$var reg 1 . BALANCE_ACTUALIZADO $end
$var reg 1 - BLOQUEO $end
$var reg 16 8 DIGITO_INTERNO [15:0] $end
$var reg 1 ) ENTREGAR_DINERO $end
$var reg 1 ( FONDOS_INSUFICIENTES $end
$var reg 3 9 INTENTOS [2:0] $end
$var reg 1 $ PIN_INCORRECTO $end
$var reg 16 : PROX_DIGITO [15:0] $end
$upscope $end
$upscope $end
$enddefinitions $end
#0
$dumpvars
bx :
b0 9
bx 8
b100100100111110000 7
b0 6
b0 5
b0 4
b0 3
b0 2
b0 1
b0 0
bz /
0.
0-
0,
b0 +
0*
0)
0(
b0 '
0&
b0 %
0$
0#
0"
0!
$end
#5000
b0 :
b0 8
1,
#10000
0,
1&
b100100100111110000 '
b100100100111110000 1
b100100100111110000 4
b110011101100111 %
b110011101100111 2
b110011101100111 5
1"
1#
#15000
1,
#20000
0,
0&
#25000
1,
#30000
b110 8
b110 :
0,
1*
b110 +
b110 0
b110 3
#35000
1,
#40000
0,
0*
#45000
1,
#50000
b1100111 8
b1100111 :
0,
1*
b111 +
b111 0
b111 3
#55000
1,
#60000
0,
0*
#65000
1,
#70000
b11001110110 8
b11001110110 :
0,
1*
b110 +
b110 0
b110 3
#75000
1,
#80000
0,
0*
#85000
1,
#90000
1.
b1001001001111100000 7
b110011101100111 8
b110011101100111 :
0,
1*
b111 +
b111 0
b111 3
#95000
1,
#100000
b0 8
b0 :
0,
0*
#105000
1,
#110000
0.
0,
b0 '
b0 1
b0 4
b0 +
b0 0
b0 3
b0 %
b0 2
b0 5
0"
0#
#115000
1,
#120000
0,
b1010101011100110000 '
b1010101011100110000 1
b1010101011100110000 4
b110011101100111 %
b110011101100111 2
b110011101100111 5
1!
1"
1#
#125000
1,
#130000
b110 8
b110 :
0,
1*
b110 +
b110 0
b110 3
#135000
1,
#140000
0,
0*
#145000
1,
#150000
b1100111 8
b1100111 :
0,
1*
b111 +
b111 0
b111 3
#155000
1,
#160000
0,
0*
#165000
1,
#170000
b11001110110 8
b11001110110 :
0,
1*
b110 +
b110 0
b110 3
#175000
1,
#180000
0,
0*
#185000
1,
#190000
1(
b110011101100111 8
b110011101100111 :
0,
1*
b111 +
b111 0
b111 3
#195000
1,
#200000
b0 8
b0 :
0,
0*
#205000
1,
#210000
0(
0,
b0 '
b0 1
b0 4
0!
b0 +
b0 0
b0 3
b0 %
b0 2
b0 5
0"
0#
#215000
1,
#220000
0,
b1001001001111100000 '
b1001001001111100000 1
b1001001001111100000 4
b110011101100111 %
b110011101100111 2
b110011101100111 5
1!
1"
1#
#225000
1,
#230000
b110 8
b110 :
0,
1*
b110 +
b110 0
b110 3
#235000
1,
#240000
0,
0*
#245000
1,
#250000
b1100111 8
b1100111 :
0,
1*
b111 +
b111 0
b111 3
#255000
1,
#260000
0,
0*
#265000
1,
#270000
b11001110110 8
b11001110110 :
0,
1*
b110 +
b110 0
b110 3
#275000
1,
#280000
0,
0*
#285000
1,
#290000
1)
1.
b0 7
b110011101100111 8
b110011101100111 :
0,
1*
b111 +
b111 0
b111 3
#295000
1,
#300000
b0 8
b0 :
0,
0*
#305000
1,
#310000
0.
0)
0,
b0 '
b0 1
b0 4
0!
b0 +
b0 0
b0 3
b0 %
b0 2
b0 5
0"
0#
#315000
1,
#320000
0,
b100100100111110000 '
b100100100111110000 1
b100100100111110000 4
b110011101100111 %
b110011101100111 2
b110011101100111 5
1"
1#
#325000
1,
#330000
b110 8
b110 :
0,
1*
b110 +
b110 0
b110 3
#335000
1,
#340000
0,
0*
#345000
1,
#350000
b1100111 8
b1100111 :
0,
1*
b111 +
b111 0
b111 3
#355000
1,
#360000
0,
0*
#365000
1,
#370000
b0 8
1$
b1 9
b0 :
0,
1*
b1 +
b1 0
b1 3
#375000
1,
#380000
0,
0*
#385000
1,
#390000
b110 8
0$
b110 :
0,
1*
b110 +
b110 0
b110 3
#395000
1,
#400000
0,
0*
#405000
1,
#410000
b1100111 8
b1100111 :
0,
1*
b111 +
b111 0
b111 3
#415000
1,
#420000
0,
0*
#425000
1,
#430000
b11001110110 8
b11001110110 :
0,
1*
b110 +
b110 0
b110 3
#435000
1,
#440000
0,
0*
#445000
1,
#450000
b1 6
b0 8
1$
b10 9
b0 :
0,
1*
b1 +
b1 0
b1 3
#455000
1,
#460000
0,
0*
#465000
1,
#470000
b110 8
0$
b110 :
0,
1*
b110 +
b110 0
b110 3
#475000
1,
#480000
0,
0*
#485000
1,
#490000
1-
b0 6
b0 8
1$
b11 9
b0 :
0,
1*
b1001 +
b1001 0
b1001 3
#495000
1,
#500000
0,
0*
#505000
1,
#510000
0,
1*
b110 +
b110 0
b110 3
#515000
1,
#520000
0,
0*
#525000
1,
#530000
0,
1*
b111 +
b111 0
b111 3
#535000
1,
#540000
0,
0*
#545000
1,
#550000
0$
0-
b0 9
0,
1*
b0 '
b0 1
b0 4
b0 +
b0 0
b0 3
0#
#555000
1,
#560000
0,
0*
#565000
1,
#570000
0,
b100100100111110000 '
b100100100111110000 1
b100100100111110000 4
1#
#575000
1,
#580000
b110 8
b110 :
0,
1*
b110 +
b110 0
b110 3
#585000
1,
#590000
0,
0*
#595000
1,
#600000
b1100111 8
b1100111 :
0,
1*
b111 +
b111 0
b111 3
#605000
1,
#610000
0,
0*
#615000
1,
#620000
b11001110110 8
b11001110110 :
0,
1*
b110 +
b110 0
b110 3
#625000
1,
#630000
0,
0*
#635000
1,
#640000
1.
b100100100111110000 7
b110011101100111 8
b110011101100111 :
0,
1*
b111 +
b111 0
b111 3
#645000
1,
#650000
b0 8
b0 :
0,
0*
